annular/__init__.py
annular/cli.py
annular/coupling.py
annular/coupling_components.py
annular/market_model.py
annular/optimization_model_manager.py
annular/tariffs.py
annular/utils.py
annular/satellite_model/__init__.py
annular/satellite_model/multi_profile_strategy.py
annular/satellite_model/reading_bids_strategy.py
annular/satellite_model/satellite_model.py
annular/satellite_model/simple_demo.py
annular-0.5.0.dist-info/licenses/LICENSE
annular-0.5.0.dist-info/licenses/NOTICE
annular-0.5.0.dist-info/METADATA
annular-0.5.0.dist-info/WHEEL
annular-0.5.0.dist-info/entry_points.txt
annular-0.5.0.dist-info/top_level.txt
annular-0.5.0.dist-info/RECORD
