Metadata-Version: 2.4
Name: annular
Version: 0.5.0
Summary: model coupling for demoses
Author-email: Christian Doh Dinga <c.dohdinga@tudelft.nl>, Sander van Rijn <s.vanrijn@esciencecenter.nl>
License: MIT License
Project-URL: Repository, https://gitlab.tudelft.nl/demoses/annular
Project-URL: Issues, https://gitlab.tudelft.nl/demoses/annular/issues
Project-URL: Changelog, https://gitlab.tudelft.nl/demoses/annular/CHANGELOG.md
Project-URL: Documentation, https://annular.readthedocs.io/en/latest/
Keywords: energy transition,flexibility
Requires-Python: >=3.10
License-File: LICENSE
License-File: NOTICE
Requires-Dist: cronian>=0.3.2
Requires-Dist: gurobipy
Requires-Dist: more_itertools
Requires-Dist: muscle3
Requires-Dist: numpy
Requires-Dist: pandas
Requires-Dist: Pyomo
Provides-Extra: dev
Requires-Dist: build; extra == "dev"
Requires-Dist: bump-my-version; extra == "dev"
Requires-Dist: coverage[toml]; extra == "dev"
Requires-Dist: highspy; extra == "dev"
Requires-Dist: jupyter; extra == "dev"
Requires-Dist: parse; extra == "dev"
Requires-Dist: pre-commit; extra == "dev"
Requires-Dist: pyprojroot; extra == "dev"
Requires-Dist: pytest; extra == "dev"
Requires-Dist: pytest-cov; extra == "dev"
Requires-Dist: pytest-xdist; extra == "dev"
Requires-Dist: ruff; extra == "dev"
Requires-Dist: tox; extra == "dev"
Provides-Extra: docs
Requires-Dist: myst_parser; extra == "docs"
Requires-Dist: sphinx; extra == "docs"
Requires-Dist: sphinx_copybutton; extra == "docs"
Requires-Dist: sphinx_rtd_theme; extra == "docs"
Requires-Dist: sphinx-autoapi; extra == "docs"
Provides-Extra: publishing
Requires-Dist: build; extra == "publishing"
Requires-Dist: twine; extra == "publishing"
Requires-Dist: wheel; extra == "publishing"
Dynamic: license-file
